fingerprints_matching/__init__.py
fingerprints_matching/fingerprints_matching.py
fingerprints_matching/minutiae_matching.py
fingerprints_matching-0.1.0.dist-info/LICENSE
fingerprints_matching-0.1.0.dist-info/METADATA
fingerprints_matching-0.1.0.dist-info/WHEEL
fingerprints_matching-0.1.0.dist-info/top_level.txt
fingerprints_matching-0.1.0.dist-info/RECORD
