Metadata-Version: 2.1
Name: fingerprints-matching
Version: 0.1.0
Summary: The package for fingerprints matching using minutiae matching algorithm
Home-page: https://github.com/msalman2890/fingerprints_matching
Author: Muhammad Salman Bediya
Author-email: juraij2890@gmail.com
License: MIT License
Platform: any
Classifier: Development Status :: 4 - Beta
Classifier: Intended Audience :: Developers
Classifier: License :: OSI Approved :: MIT License
Classifier: Operating System :: OS Independent
Classifier: Programming Language :: Python
Classifier: Topic :: Software Development :: Libraries :: Python Modules
Requires-Python: >=3.0
License-File: LICENSE
Requires-Dist: opencv-python
Requires-Dist: numpy
